pylookup/__init__.py
pylookup/__main__.py
pylookup/pylookup.py
PyLookup-0.2.2.dist-info/LICENSE.txt
PyLookup-0.2.2.dist-info/METADATA
PyLookup-0.2.2.dist-info/WHEEL
PyLookup-0.2.2.dist-info/entry_points.txt
PyLookup-0.2.2.dist-info/top_level.txt
PyLookup-0.2.2.dist-info/RECORD
