Metadata-Version: 2.1
Name: PyLookup
Version: 0.2.2
Summary: PyLookup - Fuzzy-matching table autofill tool
Home-page: https://github.com/zachbateman/pylookup.git
Author: Zach Bateman
License: MIT
Download-URL: https://github.com/zachbateman/pylookup/archive/v_0.2.2.tar.gz
Keywords: LOOKUP,VLOOKUP,TABLE,MATCHING
Platform: UNKNOWN
Classifier: Development Status :: 3 - Alpha
Classifier: License :: OSI Approved :: MIT License
Classifier: Programming Language :: Python :: 3
Classifier: Programming Language :: Python :: 3.7
Classifier: Programming Language :: Python :: 3.8
Classifier: Programming Language :: Python :: 3.9
Classifier: Programming Language :: Python :: 3.10
Requires-Dist: rapidfuzz
Requires-Dist: pandas
Requires-Dist: click
